{"nodes": [{"id": "receipttypes_activitykind", "label": "ReceiptActivityKind", "file_type": "code", "source_file": "lib/receipt/receiptTypes.ts", "source_location": null, "source_url": null, "captured_at": null, "author": null, "contributor": null}, {"id": "receipttypes_lineitem", "label": "ReceiptLineItem", "file_type": "code", "source_file": "lib/receipt/receiptTypes.ts", "source_location": null, "source_url": null, "captured_at": null, "author": null, "contributor": null}, {"id": "receipttypes_payload", "label": "ReceiptPayload", "file_type": "code", "source_file": "lib/receipt/receiptTypes.ts", "source_location": null, "source_url": null, "captured_at": null, "author": null, "contributor": null}], "edges": [{"source": "receipttypes_payload", "target": "receipttypes_lineitem", "relation": "references", "confidence": "EXTRACTED", "confidence_score": 1.0, "source_file": "lib/receipt/receiptTypes.ts", "source_location": null, "weight": 1.0}, {"source": "receipttypes_payload", "target": "receipttypes_activitykind", "relation": "references", "confidence": "EXTRACTED", "confidence_score": 1.0, "source_file": "lib/receipt/receiptTypes.ts", "source_location": null, "weight": 1.0}], "hyperedges": []}