{"nodes": [{"id": "post_review_restaurant_screen", "label": "SnapRestaurantScreen", "file_type": "code", "source_file": "app/(customer)/discover/post-review/restaurant.tsx", "source_location": null, "source_url": null, "captured_at": null, "author": null, "contributor": null}, {"id": "post_review_restaurant_submit", "label": "submit (post snap)", "file_type": "code", "source_file": "app/(customer)/discover/post-review/restaurant.tsx", "source_location": null, "source_url": null, "captured_at": null, "author": null, "contributor": null}], "edges": [{"source": "post_review_restaurant_screen", "target": "post_review_restaurant_submit", "relation": "calls", "confidence": "EXTRACTED", "confidence_score": 1.0, "source_file": "app/(customer)/discover/post-review/restaurant.tsx", "source_location": null, "weight": 1.0}, {"source": "post_review_restaurant_submit", "target": "ext_create_snap_post", "relation": "calls", "confidence": "EXTRACTED", "confidence_score": 1.0, "source_file": "app/(customer)/discover/post-review/restaurant.tsx", "source_location": null, "weight": 1.0}, {"source": "post_review_restaurant_submit", "target": "post_review_reward_screen", "relation": "references", "confidence": "EXTRACTED", "confidence_score": 1.0, "source_file": "app/(customer)/discover/post-review/restaurant.tsx", "source_location": null, "weight": 1.0}, {"source": "post_review_restaurant_screen", "target": "ext_use_current_user_id", "relation": "calls", "confidence": "EXTRACTED", "confidence_score": 1.0, "source_file": "app/(customer)/discover/post-review/restaurant.tsx", "source_location": null, "weight": 1.0}], "hyperedges": []}