{"nodes": [{"id": "reservationsettings_type", "label": "ReservationSettings Type", "file_type": "code", "source_file": "lib/owner/reservationSettings.ts", "source_location": null, "source_url": null, "captured_at": null, "author": null, "contributor": null}, {"id": "reservationsettings_default", "label": "DEFAULT_RESERVATION_SETTINGS", "file_type": "code", "source_file": "lib/owner/reservationSettings.ts", "source_location": null, "source_url": null, "captured_at": null, "author": null, "contributor": null}, {"id": "reservationsettings_picknumber", "label": "pickNumber", "file_type": "code", "source_file": "lib/owner/reservationSettings.ts", "source_location": null, "source_url": null, "captured_at": null, "author": null, "contributor": null}, {"id": "reservationsettings_normalize", "label": "normalize", "file_type": "code", "source_file": "lib/owner/reservationSettings.ts", "source_location": null, "source_url": null, "captured_at": null, "author": null, "contributor": null}, {"id": "reservationsettings_read", "label": "readReservationSettings", "file_type": "code", "source_file": "lib/owner/reservationSettings.ts", "source_location": null, "source_url": null, "captured_at": null, "author": null, "contributor": null}, {"id": "reservationsettings_write", "label": "writeReservationSettings", "file_type": "code", "source_file": "lib/owner/reservationSettings.ts", "source_location": null, "source_url": null, "captured_at": null, "author": null, "contributor": null}], "edges": [{"source": "reservationsettings_normalize", "target": "reservationsettings_picknumber", "relation": "calls", "confidence": "EXTRACTED", "confidence_score": 1.0, "source_file": "lib/owner/reservationSettings.ts", "source_location": null, "weight": 1.0}, {"source": "reservationsettings_read", "target": "reservationsettings_normalize", "relation": "calls", "confidence": "EXTRACTED", "confidence_score": 1.0, "source_file": "lib/owner/reservationSettings.ts", "source_location": null, "weight": 1.0}, {"source": "reservationsettings_write", "target": "reservationsettings_normalize", "relation": "calls", "confidence": "EXTRACTED", "confidence_score": 1.0, "source_file": "lib/owner/reservationSettings.ts", "source_location": null, "weight": 1.0}, {"source": "reservationsettings_read", "target": "reservationsettings_default", "relation": "references", "confidence": "EXTRACTED", "confidence_score": 1.0, "source_file": "lib/owner/reservationSettings.ts", "source_location": null, "weight": 1.0}, {"source": "reservationsettings_default", "target": "reservationsettings_type", "relation": "implements", "confidence": "EXTRACTED", "confidence_score": 1.0, "source_file": "lib/owner/reservationSettings.ts", "source_location": null, "weight": 1.0}, {"source": "reservationsettings_read", "target": "reservationsettings_type", "relation": "references", "confidence": "EXTRACTED", "confidence_score": 1.0, "source_file": "lib/owner/reservationSettings.ts", "source_location": null, "weight": 1.0}, {"source": "reservationsettings_write", "target": "reservationsettings_type", "relation": "references", "confidence": "EXTRACTED", "confidence_score": 1.0, "source_file": "lib/owner/reservationSettings.ts", "source_location": null, "weight": 1.0}, {"source": "reservationsettings_read", "target": "reservationsettings_write", "relation": "shares_data_with", "confidence": "INFERRED", "confidence_score": 0.95, "source_file": "lib/owner/reservationSettings.ts", "source_location": null, "weight": 1.0}, {"source": "reservationsettings_default", "target": "rolepermissionssettings_defaultperms", "relation": "conceptually_related_to", "confidence": "INFERRED", "confidence_score": 0.65, "source_file": "lib/owner/reservationSettings.ts", "source_location": null, "weight": 1.0}], "hyperedges": []}