{"nodes": [{"id": "billing-address_screen", "label": "BillingAddressScreen", "file_type": "code", "source_file": "app/(staff)/billing-address.tsx", "source_location": null, "source_url": null, "captured_at": null, "author": null, "contributor": null}, {"id": "billing-address_onsave", "label": "onSave billing address handler", "file_type": "code", "source_file": "app/(staff)/billing-address.tsx", "source_location": null, "source_url": null, "captured_at": null, "author": null, "contributor": null}, {"id": "billing-address_restaurantbillingaddress", "label": "RestaurantBillingAddress (storage helpers)", "file_type": "code", "source_file": "app/(staff)/billing-address.tsx", "source_location": null, "source_url": null, "captured_at": null, "author": null, "contributor": null}], "edges": [{"source": "billing-address_screen", "target": "billing-address_onsave", "relation": "calls", "confidence": "EXTRACTED", "confidence_score": 1.0, "source_file": "app/(staff)/billing-address.tsx", "source_location": null, "weight": 1.0}, {"source": "billing-address_onsave", "target": "billing-address_restaurantbillingaddress", "relation": "calls", "confidence": "EXTRACTED", "confidence_score": 1.0, "source_file": "app/(staff)/billing-address.tsx", "source_location": null, "weight": 1.0}, {"source": "billing-address_screen", "target": "billing-address_restaurantbillingaddress", "relation": "references", "confidence": "EXTRACTED", "confidence_score": 1.0, "source_file": "app/(staff)/billing-address.tsx", "source_location": null, "weight": 1.0}, {"source": "billing-address_onsave", "target": "expenses_screen", "relation": "conceptually_related_to", "confidence": "INFERRED", "confidence_score": 0.55, "source_file": "app/(staff)/billing-address.tsx", "source_location": null, "weight": 1.0}], "hyperedges": []}