{"nodes": [{"id": "promotions_index_screen", "label": "PromosScreen", "file_type": "code", "source_file": "app/(staff)/promotions/index.tsx", "source_location": "L485-745", "source_url": null, "captured_at": null, "author": null, "contributor": null}, {"id": "promotions_map_promo_status", "label": "mapPromoStatus", "file_type": "code", "source_file": "app/(staff)/promotions/index.tsx", "source_location": "L35-40", "source_url": null, "captured_at": null, "author": null, "contributor": null}, {"id": "promotions_map_row", "label": "mapPromotionRowToOwnerPromotion", "file_type": "code", "source_file": "app/(staff)/promotions/index.tsx", "source_location": "L42-94", "source_url": null, "captured_at": null, "author": null, "contributor": null}, {"id": "promotions_format_promo_type", "label": "formatPromoType", "file_type": "code", "source_file": "app/(staff)/promotions/index.tsx", "source_location": "L108-125", "source_url": null, "captured_at": null, "author": null, "contributor": null}, {"id": "promotions_format_status", "label": "formatStatus", "file_type": "code", "source_file": "app/(staff)/promotions/index.tsx", "source_location": "L127-140", "source_url": null, "captured_at": null, "author": null, "contributor": null}, {"id": "promotions_format_audience", "label": "formatAudience", "file_type": "code", "source_file": "app/(staff)/promotions/index.tsx", "source_location": "L146-148", "source_url": null, "captured_at": null, "author": null, "contributor": null}, {"id": "promotions_format_where", "label": "formatWhere", "file_type": "code", "source_file": "app/(staff)/promotions/index.tsx", "source_location": "L150-157", "source_url": null, "captured_at": null, "author": null, "contributor": null}], "edges": [{"source": "promotions_index_screen", "target": "lib_demo_mode", "relation": "calls", "confidence": "EXTRACTED", "confidence_score": 1.0, "source_file": "app/(staff)/promotions/index.tsx", "source_location": "L496", "weight": 1.0}, {"source": "promotions_index_screen", "target": "lib_use_owner_scope", "relation": "calls", "confidence": "EXTRACTED", "confidence_score": 1.0, "source_file": "app/(staff)/promotions/index.tsx", "source_location": "L492", "weight": 1.0}, {"source": "promotions_index_screen", "target": "lib_fetch_active_promotions", "relation": "calls", "confidence": "EXTRACTED", "confidence_score": 1.0, "source_file": "app/(staff)/promotions/index.tsx", "source_location": "L503", "weight": 1.0}, {"source": "promotions_index_screen", "target": "promotions_map_row", "relation": "calls", "confidence": "EXTRACTED", "confidence_score": 1.0, "source_file": "app/(staff)/promotions/index.tsx", "source_location": "L507", "weight": 1.0}, {"source": "promotions_map_row", "target": "promotions_map_promo_status", "relation": "calls", "confidence": "EXTRACTED", "confidence_score": 1.0, "source_file": "app/(staff)/promotions/index.tsx", "source_location": "L44", "weight": 1.0}, {"source": "promotions_index_screen", "target": "promotions_format_promo_type", "relation": "calls", "confidence": "EXTRACTED", "confidence_score": 1.0, "source_file": "app/(staff)/promotions/index.tsx", "source_location": "L597", "weight": 1.0}, {"source": "promotions_index_screen", "target": "promotions_format_status", "relation": "calls", "confidence": "EXTRACTED", "confidence_score": 1.0, "source_file": "app/(staff)/promotions/index.tsx", "source_location": "L606", "weight": 1.0}, {"source": "promotions_index_screen", "target": "promotions_format_audience", "relation": "calls", "confidence": "EXTRACTED", "confidence_score": 1.0, "source_file": "app/(staff)/promotions/index.tsx", "source_location": "L633", "weight": 1.0}, {"source": "promotions_index_screen", "target": "promotions_format_where", "relation": "calls", "confidence": "EXTRACTED", "confidence_score": 1.0, "source_file": "app/(staff)/promotions/index.tsx", "source_location": "L639", "weight": 1.0}, {"source": "promotions_index_screen", "target": "promotions_new_screen", "relation": "references", "confidence": "EXTRACTED", "confidence_score": 1.0, "source_file": "app/(staff)/promotions/index.tsx", "source_location": "L729", "weight": 1.0}, {"source": "promotions_index_screen", "target": "promotions_new_screen", "relation": "conceptually_related_to", "confidence": "EXTRACTED", "confidence_score": 1.0, "source_file": "app/(staff)/promotions/index.tsx", "source_location": "L729", "weight": 1.0}], "hyperedges": []}