{"nodes": [{"id": "lib_upload_restaurant_photo", "label": "uploadRestaurantPhoto", "file_type": "code", "source_file": "lib/owner/uploadRestaurantPhoto.ts", "source_location": null, "source_url": null, "captured_at": null, "author": null, "contributor": null}, {"id": "uploadrestaurantphoto_args", "label": "UploadRestaurantPhotoArgs Type", "file_type": "code", "source_file": "lib/owner/uploadRestaurantPhoto.ts", "source_location": null, "source_url": null, "captured_at": null, "author": null, "contributor": null}, {"id": "uploadrestaurantphoto_upload", "label": "uploadRestaurantPhoto", "file_type": "code", "source_file": "lib/owner/uploadRestaurantPhoto.ts", "source_location": null, "source_url": null, "captured_at": null, "author": null, "contributor": null}], "edges": [{"source": "uploadrestaurantphoto_upload", "target": "uploadrestaurantphoto_args", "relation": "references", "confidence": "EXTRACTED", "confidence_score": 1.0, "source_file": "lib/owner/uploadRestaurantPhoto.ts", "source_location": null, "weight": 1.0}, {"source": "uploadrestaurantphoto_upload", "target": "uploadeventmedia_upload", "relation": "semantically_similar_to", "confidence": "INFERRED", "confidence_score": 0.85, "source_file": "lib/owner/uploadRestaurantPhoto.ts", "source_location": null, "weight": 1.0}], "hyperedges": []}