{"nodes": [{"id": "users_stevengeorgy_mobile_seatly_v2_5_lib_map_geo_ts", "label": "geo.ts", "file_type": "code", "source_file": "/Users/stevengeorgy/mobile-seatly-v2-5/lib/map/geo.ts", "source_location": "L1"}, {"id": "map_geo_haversinemeters", "label": "haversineMeters()", "file_type": "code", "source_file": "/Users/stevengeorgy/mobile-seatly-v2-5/lib/map/geo.ts", "source_location": "L4"}, {"id": "map_geo_hasfinitecoords", "label": "hasFiniteCoords()", "file_type": "code", "source_file": "/Users/stevengeorgy/mobile-seatly-v2-5/lib/map/geo.ts", "source_location": "L21"}, {"id": "map_geo_formatdistancemeters", "label": "formatDistanceMeters()", "file_type": "code", "source_file": "/Users/stevengeorgy/mobile-seatly-v2-5/lib/map/geo.ts", "source_location": "L34"}], "edges": [{"source": "users_stevengeorgy_mobile_seatly_v2_5_lib_map_geo_ts", "target": "map_geo_haversinemeters", "relation": "contains", "confidence": "EXTRACTED", "source_file": "/Users/stevengeorgy/mobile-seatly-v2-5/lib/map/geo.ts", "source_location": "L4", "weight": 1.0}, {"source": "users_stevengeorgy_mobile_seatly_v2_5_lib_map_geo_ts", "target": "map_geo_hasfinitecoords", "relation": "contains", "confidence": "EXTRACTED", "source_file": "/Users/stevengeorgy/mobile-seatly-v2-5/lib/map/geo.ts", "source_location": "L21", "weight": 1.0}, {"source": "users_stevengeorgy_mobile_seatly_v2_5_lib_map_geo_ts", "target": "map_geo_formatdistancemeters", "relation": "contains", "confidence": "EXTRACTED", "source_file": "/Users/stevengeorgy/mobile-seatly-v2-5/lib/map/geo.ts", "source_location": "L34", "weight": 1.0}], "raw_calls": [{"caller_nid": "map_geo_haversinemeters", "callee": "sin", "is_member_call": true, "source_file": "/Users/stevengeorgy/mobile-seatly-v2-5/lib/map/geo.ts", "source_location": "L10"}, {"caller_nid": "map_geo_haversinemeters", "callee": "sin", "is_member_call": true, "source_file": "/Users/stevengeorgy/mobile-seatly-v2-5/lib/map/geo.ts", "source_location": "L10"}, {"caller_nid": "map_geo_haversinemeters", "callee": "cos", "is_member_call": true, "source_file": "/Users/stevengeorgy/mobile-seatly-v2-5/lib/map/geo.ts", "source_location": "L11"}, {"caller_nid": "map_geo_haversinemeters", "callee": "cos", "is_member_call": true, "source_file": "/Users/stevengeorgy/mobile-seatly-v2-5/lib/map/geo.ts", "source_location": "L11"}, {"caller_nid": "map_geo_haversinemeters", "callee": "sin", "is_member_call": true, "source_file": "/Users/stevengeorgy/mobile-seatly-v2-5/lib/map/geo.ts", "source_location": "L11"}, {"caller_nid": "map_geo_haversinemeters", "callee": "sin", "is_member_call": true, "source_file": "/Users/stevengeorgy/mobile-seatly-v2-5/lib/map/geo.ts", "source_location": "L11"}, {"caller_nid": "map_geo_haversinemeters", "callee": "atan2", "is_member_call": true, "source_file": "/Users/stevengeorgy/mobile-seatly-v2-5/lib/map/geo.ts", "source_location": "L12"}, {"caller_nid": "map_geo_haversinemeters", "callee": "sqrt", "is_member_call": true, "source_file": "/Users/stevengeorgy/mobile-seatly-v2-5/lib/map/geo.ts", "source_location": "L12"}, {"caller_nid": "map_geo_haversinemeters", "callee": "sqrt", "is_member_call": true, "source_file": "/Users/stevengeorgy/mobile-seatly-v2-5/lib/map/geo.ts", "source_location": "L12"}, {"caller_nid": "map_geo_hasfinitecoords", "callee": "isFinite", "is_member_call": true, "source_file": "/Users/stevengeorgy/mobile-seatly-v2-5/lib/map/geo.ts", "source_location": "L27"}, {"caller_nid": "map_geo_hasfinitecoords", "callee": "isFinite", "is_member_call": true, "source_file": "/Users/stevengeorgy/mobile-seatly-v2-5/lib/map/geo.ts", "source_location": "L28"}, {"caller_nid": "map_geo_hasfinitecoords", "callee": "abs", "is_member_call": true, "source_file": "/Users/stevengeorgy/mobile-seatly-v2-5/lib/map/geo.ts", "source_location": "L29"}, {"caller_nid": "map_geo_hasfinitecoords", "callee": "abs", "is_member_call": true, "source_file": "/Users/stevengeorgy/mobile-seatly-v2-5/lib/map/geo.ts", "source_location": "L30"}, {"caller_nid": "map_geo_formatdistancemeters", "callee": "isFinite", "is_member_call": true, "source_file": "/Users/stevengeorgy/mobile-seatly-v2-5/lib/map/geo.ts", "source_location": "L35"}, {"caller_nid": "map_geo_formatdistancemeters", "callee": "max", "is_member_call": true, "source_file": "/Users/stevengeorgy/mobile-seatly-v2-5/lib/map/geo.ts", "source_location": "L37"}, {"caller_nid": "map_geo_formatdistancemeters", "callee": "round", "is_member_call": true, "source_file": "/Users/stevengeorgy/mobile-seatly-v2-5/lib/map/geo.ts", "source_location": "L37"}, {"caller_nid": "map_geo_formatdistancemeters", "callee": "round", "is_member_call": true, "source_file": "/Users/stevengeorgy/mobile-seatly-v2-5/lib/map/geo.ts", "source_location": "L40"}, {"caller_nid": "map_geo_formatdistancemeters", "callee": "toFixed", "is_member_call": true, "source_file": "/Users/stevengeorgy/mobile-seatly-v2-5/lib/map/geo.ts", "source_location": "L40"}]}